cognee_community_vector_adapter_opensearch/__init__.py
cognee_community_vector_adapter_opensearch/opensearch_adapter.py
cognee_community_vector_adapter_opensearch/register.py
cognee_community_vector_adapter_opensearch/tests/__init__.py
cognee_community_vector_adapter_opensearch/tests/test_opensearch.py
cognee_community_vector_adapter_opensearch/tests/test_data/Natural_language_processing.txt
cognee_community_vector_adapter_opensearch-1.0.0.dist-info/METADATA
cognee_community_vector_adapter_opensearch-1.0.0.dist-info/WHEEL
cognee_community_vector_adapter_opensearch-1.0.0.dist-info/RECORD
