Metadata-Version: 2.4
Name: cognee-community-vector-adapter-opensearch
Version: 1.0.0
Summary: OpenSearch vector database adapter for cognee
Project-URL: Homepage, https://www.cognee.ai
Project-URL: Repository, https://github.com/topoteretes/cognee-community
Requires-Python: <=3.13,>=3.10
Requires-Dist: cognee>=0.2.4
Requires-Dist: opensearch-py==3.0.0
